pixel_artist/__about__.py
pixel_artist/__init__.py
pixel_artist/__main__.py
pixel_artist/constants.py
pixel_artist/core.py
pixel_artist/parser.py
pixel_artist/palette/3bit.palette
pixel_artist/palette/8bit.palette
pixel_artist/palette/9bit.palette
pixel_artist-0.0.6.dist-info/LICENSE
pixel_artist-0.0.6.dist-info/METADATA
pixel_artist-0.0.6.dist-info/WHEEL
pixel_artist-0.0.6.dist-info/entry_points.txt
pixel_artist-0.0.6.dist-info/top_level.txt
pixel_artist-0.0.6.dist-info/RECORD
