Metadata-Version: 2.1
Name: pixel-artist
Version: 0.0.6
Summary: A command line utility to build pixelated images.
Home-page: https://github.com/alexpnt/pixel-artist
Author: Alexandre Pinto
Author-email: alexandpinto@gmail.com
License: MIT
Project-URL: Source, https://github.com/alexpnt/pixel-artist
Project-URL: Documentation, https://github.com/alexpnt/pixel-artist
Project-URL: Bug Tracker, https://github.com/alexpnt/pixel-artist/issues
Keywords: python,command-line,console,cmd,pixel-art,pixel,image-processing
Platform: UNKNOWN
Classifier: Development Status :: 5 - Production/Stable
Classifier: Environment :: Console
Classifier: Intended Audience :: End Users/Desktop
Classifier: Intended Audience :: Developers
Classifier: License :: OSI Approved :: MIT License
Classifier: Operating System :: OS Independent
Classifier: Programming Language :: Python :: 3 :: Only
Classifier: Programming Language :: Python :: 3.6
Classifier: Programming Language :: Python :: 3.8
Classifier: Programming Language :: Python :: 3.9
Classifier: Programming Language :: Python :: Implementation :: CPython
Classifier: Topic :: Multimedia :: Graphics
Classifier: Topic :: Terminals
Classifier: Topic :: Utilities
Requires-Python: >=3.6
License-File: LICENSE
Requires-Dist: Pillow (==9.0.1)
Requires-Dist: colormath (==3.0.0)
